nomad_camels_driver_keithley_237/keithley_237.py
nomad_camels_driver_keithley_237/keithley_237_ophyd.py
nomad_camels_driver_keithley_237-0.1.1.dist-info/LICENSE.txt
nomad_camels_driver_keithley_237-0.1.1.dist-info/METADATA
nomad_camels_driver_keithley_237-0.1.1.dist-info/WHEEL
nomad_camels_driver_keithley_237-0.1.1.dist-info/top_level.txt
nomad_camels_driver_keithley_237-0.1.1.dist-info/RECORD
